neuralworks_lib/__init__.py
neuralworks_lib/dataset.py
neuralworks_lib/model.py
neuralworks_lib/neuannotation.py
neuralworks_lib/neuenv.py
neuralworks_lib/neujson.py
neuralworks_lib/neutable.py
neuralworks_lib/neutils.py
neuralworks_lib/test_dataset.py
neuralworks_lib/test_dataset_detection.py
neuralworks_lib/torch_helper.py
neuralworks_lib-0.0.2.dist-info/METADATA
neuralworks_lib-0.0.2.dist-info/WHEEL
neuralworks_lib-0.0.2.dist-info/top_level.txt
neuralworks_lib-0.0.2.dist-info/RECORD
