Metadata-Version: 2.1
Name: neuralworks-lib
Version: 0.0.2
Summary: neuralworks lib test
Home-page: https://github.com/Neuralworks-io
Author: UNKNOWN
Author-email: UNKNOWN
License: UNKNOWN
Download-URL: https://github.com/Neuralworks-io/archive/0.0.tar.gz
Platform: UNKNOWN
